LICENSE
paralleller/__init__.py
paralleller/cli.py
paralleller/error.py
paralleller/jl.py
paralleller/log.py
paralleller/mpi.py
paralleller/multiprocessing.py
paralleller/paralleller.py
paralleller/pool.py
paralleller/py.typed
paralleller/serial.py
paralleller/utils.py
paralleller-0.0.4.dist-info/entry_points.txt
paralleller-0.0.4.dist-info/LICENSE
paralleller-0.0.4.dist-info/WHEEL
paralleller-0.0.4.dist-info/METADATA
paralleller-0.0.4.dist-info/RECORD
